hello_package/__init__.py
hello_package/main.py
hello_package_taeil-0.1.0.dist-info/METADATA
hello_package_taeil-0.1.0.dist-info/WHEEL
hello_package_taeil-0.1.0.dist-info/top_level.txt
hello_package_taeil-0.1.0.dist-info/RECORD
